strength/__init__.py
strength/yieldstrength.py
pypremod_strength-0.1.6.dist-info/LICENSE.txt
pypremod_strength-0.1.6.dist-info/METADATA
pypremod_strength-0.1.6.dist-info/WHEEL
pypremod_strength-0.1.6.dist-info/top_level.txt
pypremod_strength-0.1.6.dist-info/RECORD
