Metadata-Version: 2.1
Name: pypremod-strength
Version: 0.1.6
Summary: Python package for strength models
Home-page: https://www.sintef.no/
License: UNKNOWN
Platform: UNKNOWN
License-File: LICENSE.txt
